s3_dumps/__init__.py
s3_dumps/archive.py
s3_dumps/connect.py
s3_dumps/mysql_to_s3.py
s3_dumps/postgres_to_s3.py
s3_dumps/redis_to_s3.py
s3_dumps/utils.py
s3_dumps-0.2.2.data/scripts/postgres_to_s3.py
s3_dumps-0.2.2.data/scripts/redis_to_s3.py
s3_dumps-0.2.2.dist-info/METADATA
s3_dumps-0.2.2.dist-info/WHEEL
s3_dumps-0.2.2.dist-info/entry_points.txt
s3_dumps-0.2.2.dist-info/top_level.txt
s3_dumps-0.2.2.dist-info/RECORD
