Metadata-Version: 2.1
Name: s3-dumps
Version: 0.2.2
Summary: A package for backup DB and store in s3
Home-page: https://github.com/rakeshgunduka/s3_dumps
Author: Reck31
Author-email: rakesh.gunduka@gmail.com
License: MIT
Keywords: s3,backup,postgres,redis,digitaloceanspaces,aws
Platform: UNKNOWN
Classifier: Development Status :: 1 - Planning
Classifier: Intended Audience :: System Administrators
Classifier: License :: OSI Approved :: MIT License
Classifier: Operating System :: OS Independent
Classifier: Programming Language :: Python
Classifier: Programming Language :: Python :: 3 :: Only
Requires-Dist: boto3
Requires-Dist: pytz
